mkdocs_bulma_theme/404.html
mkdocs_bulma_theme/__init__.py
mkdocs_bulma_theme/base.html
mkdocs_bulma_theme/css/theme.css
mkdocs_bulma_theme/css/theme.css.map
mkdocs_bulma_theme/footer.html
mkdocs_bulma_theme/img/favicon.ico
mkdocs_bulma_theme/js/theme.js
mkdocs_bulma_theme/main.html
mkdocs_bulma_theme/mkdocs_theme.yml
mkdocs_bulma_theme/nav.html
mkdocs_bulma_theme/sass/bulma/LICENSE
mkdocs_bulma_theme/sass/bulma/README.md
mkdocs_bulma_theme/sass/bulma/bulma.sass
mkdocs_bulma_theme/sass/bulma/package.json
mkdocs_bulma_theme/sass/bulma/sass/base/_all.sass
mkdocs_bulma_theme/sass/bulma/sass/base/animations.sass
mkdocs_bulma_theme/sass/bulma/sass/base/generic.sass
mkdocs_bulma_theme/sass/bulma/sass/base/helpers.sass
mkdocs_bulma_theme/sass/bulma/sass/base/minireset.sass
mkdocs_bulma_theme/sass/bulma/sass/components/_all.sass
mkdocs_bulma_theme/sass/bulma/sass/components/breadcrumb.sass
mkdocs_bulma_theme/sass/bulma/sass/components/card.sass
mkdocs_bulma_theme/sass/bulma/sass/components/dropdown.sass
mkdocs_bulma_theme/sass/bulma/sass/components/level.sass
mkdocs_bulma_theme/sass/bulma/sass/components/media.sass
mkdocs_bulma_theme/sass/bulma/sass/components/menu.sass
mkdocs_bulma_theme/sass/bulma/sass/components/message.sass
mkdocs_bulma_theme/sass/bulma/sass/components/modal.sass
mkdocs_bulma_theme/sass/bulma/sass/components/navbar.sass
mkdocs_bulma_theme/sass/bulma/sass/components/pagination.sass
mkdocs_bulma_theme/sass/bulma/sass/components/panel.sass
mkdocs_bulma_theme/sass/bulma/sass/components/tabs.sass
mkdocs_bulma_theme/sass/bulma/sass/elements/_all.sass
mkdocs_bulma_theme/sass/bulma/sass/elements/box.sass
mkdocs_bulma_theme/sass/bulma/sass/elements/button.sass
mkdocs_bulma_theme/sass/bulma/sass/elements/container.sass
mkdocs_bulma_theme/sass/bulma/sass/elements/content.sass
mkdocs_bulma_theme/sass/bulma/sass/elements/form.sass
mkdocs_bulma_theme/sass/bulma/sass/elements/icon.sass
mkdocs_bulma_theme/sass/bulma/sass/elements/image.sass
mkdocs_bulma_theme-1.0.0b3.dist-info/METADATA
mkdocs_bulma_theme-1.0.0b3.dist-info/entry_points.txt
mkdocs_bulma_theme-1.0.0b3.dist-info/WHEEL
mkdocs_bulma_theme-1.0.0b3.dist-info/LICENSE
mkdocs_bulma_theme-1.0.0b3.dist-info/RECORD
